{
    "_links": {
        "self": {
            "href": "http:\/\/default\/admin\/structure\/menu\/item\/8\/edit?_format=hal_json"
        },
        "type": {
            "href": "http:\/\/drupal.org\/rest\/type\/menu_link_content\/menu_link_content"
        }
    },
    "id": [
        {
            "value": 8
        }
    ],
    "uuid": [
        {
            "value": "6e7e7ee5-d1c6-456b-a8b2-23ae44e28ae7"
        }
    ],
    "langcode": [
        {
            "value": "en",
            "lang": "en"
        }
    ],
    "bundle": [
        {
            "value": "menu_link_content"
        }
    ],
    "title": [
        {
            "value": "Alerts and notifications",
            "lang": "en"
        }
    ],
    "menu_name": [
        {
            "value": "menu-footer-menu"
        }
    ],
    "link": [
        {
            "uri": "internal:\/",
            "title": "",
            "options": []
        }
    ],
    "external": [
        {
            "value": false
        }
    ],
    "rediscover": [
        {
            "value": true
        }
    ],
    "weight": [
        {
            "value": -46
        }
    ],
    "expanded": [
        {
            "value": false
        }
    ],
    "enabled": [
        {
            "value": true
        }
    ],
    "changed": [
        {
            "value": "2018-08-17T12:42:26+00:00",
            "lang": "en",
            "format": "Y-m-d\\TH:i:sP"
        }
    ],
    "default_langcode": [
        {
            "value": true,
            "lang": "en"
        }
    ],
    "metatag": [
        {
            "value": {
                "title": "| Boston.gov",
                "twitter_cards_type": "summary",
                "og_site_name": "Boston.gov",
                "shortlink": "http:\/\/default\/",
                "canonical_url": "http:\/\/default\/",
                "og_type": "article",
                "og_url": "http:\/\/default\/",
                "generator": "Drupal 8 (http:\/\/drupal.org)",
                "twitter_cards_page_url": "http:\/\/default\/",
                "apple_touch_icon_180x180": "\/themes\/custom\/bos_theme\/images\/apple-touch-icon.png",
                "apple_touch_icon_precomposed_180x180": "\/themes\/custom\/bos_theme\/images\/apple-touch-icon-precomposed.png"
            }
        }
    ]
}